__init__.py
fruxon/__init__.py
fruxon/__main__.py
fruxon/cli.py
fruxon/fruxon.py
fruxon/utils.py
fruxon-0.1.1.dist-info/licenses/LICENSE
fruxon-0.1.1.dist-info/METADATA
fruxon-0.1.1.dist-info/WHEEL
fruxon-0.1.1.dist-info/entry_points.txt
fruxon-0.1.1.dist-info/top_level.txt
fruxon-0.1.1.dist-info/RECORD
